dss_python_sdk/__init__.py
dss_python_sdk/db_utils.py
dss_python_sdk/dss_utils.py
dss_python_sdk/http_utils.py
dss_python_sdk/memory_utils.py
dss_python_sdk/misc_utils.py
dss_python_sdk/queue_utils.py
dss_python_sdk/test_db_utils.py
dss_python_sdk/test_memory_utils.py
dss_python_sdk/test_misc_utils.py
dss_python_sdk/test_queue_utils.py
dss_python_sdk-0.0.9.dist-info/METADATA
dss_python_sdk-0.0.9.dist-info/WHEEL
dss_python_sdk-0.0.9.dist-info/top_level.txt
dss_python_sdk-0.0.9.dist-info/RECORD
