Metadata-Version: 2.1
Name: dss-python-sdk
Version: 0.0.9
Summary: data source management system  python sdk
Home-page: UNKNOWN
Author: vivian
Author-email: UNKNOWN
License: UNKNOWN
Platform: UNKNOWN
Requires-Dist: PyYAML (>=5.3.1)
